pycodi/CODI.py
pycodi/__init__.py
pycodi-0.0.1.dist-info/METADATA
pycodi-0.0.1.dist-info/WHEEL
pycodi-0.0.1.dist-info/top_level.txt
pycodi-0.0.1.dist-info/RECORD
