Metadata-Version: 2.1
Name: pycodi
Version: 0.0.1
Summary: Contextual Out-of-Distribution Integration
Home-page: https://github.com/tarek-eissa/codi
Author: Tarek Eissa
License: UNKNOWN
Platform: UNKNOWN
